albanian_lang/__init__.py
albanian_lang/gjuha.py
albanian_lang-0.0.1.dist-info/LICENSE
albanian_lang-0.0.1.dist-info/METADATA
albanian_lang-0.0.1.dist-info/WHEEL
albanian_lang-0.0.1.dist-info/top_level.txt
albanian_lang-0.0.1.dist-info/RECORD
