Metadata-Version: 2.1
Name: albanian-lang
Version: 0.0.1
Summary: Albanian language package
Home-page: https://github.com/florijanqosja
Author: Florijan Qosja
Author-email: florijanqosja@gmail.com
Project-URL: Bug Tracker, https://github.com/pypa/sampleproject/issues
Classifier: Programming Language :: Python :: 3
Classifier: License :: OSI Approved :: MIT License
Classifier: Operating System :: OS Independent
Requires-Python: >=3.6
License-File: LICENSE
